mcp_server_canteen/__init__.py
mcp_server_canteen/server.py
mcp_server_canteen-0.2.8.dist-info/METADATA
mcp_server_canteen-0.2.8.dist-info/WHEEL
mcp_server_canteen-0.2.8.dist-info/entry_points.txt
mcp_server_canteen-0.2.8.dist-info/licenses/LICENSE
mcp_server_canteen-0.2.8.dist-info/RECORD
