Metadata-Version: 2.4
Name: mcp-server-canteen
Version: 0.2.8
Summary: MCP Server for Canteen Data
License-Expression: MIT
License-File: LICENSE
Keywords: api,canteen,mcp
Requires-Python: >=3.10
Requires-Dist: httpx>=0.24.0
Requires-Dist: mcp[cli]>=1.6.0
Provides-Extra: dev
Requires-Dist: black>=23.0.0; extra == 'dev'
Requires-Dist: isort>=5.0.0; extra == 'dev'
Requires-Dist: pytest>=7.0.0; extra == 'dev'
